odoo/addons/product_firmware_version/README.rst
odoo/addons/product_firmware_version/__init__.py
odoo/addons/product_firmware_version/__manifest__.py
odoo/addons/product_firmware_version/models/__init__.py
odoo/addons/product_firmware_version/models/product.py
odoo/addons/product_firmware_version/static/description/icon.png
odoo/addons/product_firmware_version/views/product_view.xml
odoo11_addon_product_firmware_version-11.0.1.0.0.dist-info/DESCRIPTION.rst
odoo11_addon_product_firmware_version-11.0.1.0.0.dist-info/METADATA
odoo11_addon_product_firmware_version-11.0.1.0.0.dist-info/RECORD
odoo11_addon_product_firmware_version-11.0.1.0.0.dist-info/WHEEL
odoo11_addon_product_firmware_version-11.0.1.0.0.dist-info/metadata.json
odoo11_addon_product_firmware_version-11.0.1.0.0.dist-info/top_level.txt
